django_log_hub-1.0.6.dist-info/licenses/LICENSE
log_hub/__init__.py
log_hub/apps.py
log_hub/services.py
log_hub/urls.py
log_hub/views.py
log_hub/locale/tr/LC_MESSAGES/django.mo
log_hub/locale/tr/LC_MESSAGES/django.po
log_hub/templates/log_hub/logging.html
log_hub/templates/log_hub/test_logging.html
django_log_hub-1.0.6.dist-info/METADATA
django_log_hub-1.0.6.dist-info/WHEEL
django_log_hub-1.0.6.dist-info/top_level.txt
django_log_hub-1.0.6.dist-info/RECORD
