Metadata-Version: 2.4
Name: django-log-hub
Version: 1.0.6
Summary: Advanced logging and monitoring module for Django projects with centralized logging system
Home-page: https://github.com/eneshazr/django-log-hub
Author: Enes HAZIR
License: MIT
Project-URL: Homepage, https://github.com/eneshazr/django-log-hub
Project-URL: Documentation, https://github.com/eneshazr/django-log-hub#readme
Project-URL: Repository, https://github.com/eneshazr/django-log-hub
Project-URL: Bug Tracker, https://github.com/eneshazr/django-log-hub/issues
Keywords: django,logging,admin,logs,monitoring,debug,centralized logging,context manager,decorator
Classifier: Development Status :: 5 - Production/Stable
Classifier: Intended Audience :: Developers
Classifier: License :: OSI Approved :: MIT License
Classifier: Operating System :: OS Independent
Classifier: Programming Language :: Python :: 3
Classifier: Programming Language :: Python :: 3.8
Classifier: Programming Language :: Python :: 3.9
Classifier: Programming Language :: Python :: 3.10
Classifier: Programming Language :: Python :: 3.11
Classifier: Programming Language :: Python :: 3.12
Classifier: Programming Language :: Python :: 3.13
Classifier: Framework :: Django
Classifier: Framework :: Django :: 3.2
Classifier: Framework :: Django :: 4.0
Classifier: Framework :: Django :: 4.1
Classifier: Framework :: Django :: 4.2
Classifier: Framework :: Django :: 5.0
Classifier: Framework :: Django :: 5.1
Classifier: Framework :: Django :: 5.2
Classifier: Topic :: System :: Logging
Classifier: Topic :: Software Development :: Libraries :: Python Modules
Requires-Python: >=3.8
License-File: LICENSE
Requires-Dist: python-json-logger>=2.0.0
Provides-Extra: dev
Requires-Dist: pytest>=7.0; extra == "dev"
Requires-Dist: pytest-django>=4.5; extra == "dev"
Requires-Dist: black>=23.0; extra == "dev"
Requires-Dist: flake8>=6.0; extra == "dev"
Requires-Dist: isort>=5.0; extra == "dev"
Dynamic: author
Dynamic: home-page
Dynamic: license-file
Dynamic: requires-python
